pypterminals/__init__.py
pypterminals/terminal.py
pypterminals/test.py
Pypterminals-0.0.1.dist-info/METADATA
Pypterminals-0.0.1.dist-info/WHEEL
Pypterminals-0.0.1.dist-info/top_level.txt
Pypterminals-0.0.1.dist-info/RECORD
