Metadata-Version: 2.1
Name: Pypterminals
Version: 0.0.1
Summary: A graphic process terminal, to solve the process only one command terminal problem
Home-page: UNKNOWN
Author: binn
Author-email: binn@pigwow.cn
License: UNKNOWN
Platform: UNKNOWN
Classifier: Programming Language :: Python :: 3
